Metadata-Version: 1.1
Name: dpys
Version: 3.0.2
Summary: A library to simplify discord.py
Home-page: https://sites.google.com/view/dpys
Author: George Luca
Author-email: fixingg@gmail.com
License: MIT
Keywords: discord
Platform: UNKNOWN
Classifier: Development Status :: 5 - Production/Stable
Classifier: Intended Audience :: Education
Classifier: License :: OSI Approved :: MIT License
Classifier: Programming Language :: Python :: 3
